am2r_yams/__init__.py
am2r_yams/wrapper.py
am2r_yams/__pyinstaller/__init__.py
am2r_yams/__pyinstaller/hook-am2r_yams.py
am2r_yams/yams/ICSharpCode.SharpZipLib.dll
am2r_yams/yams/Macross.Json.Extensions.dll
am2r_yams/yams/Microsoft.Win32.SystemEvents.dll
am2r_yams/yams/NaturalSort.Extension.dll
am2r_yams/yams/PropertyChanged.dll
am2r_yams/yams/SixLabors.ImageSharp.dll
am2r_yams/yams/System.Drawing.Common.dll
am2r_yams/yams/UndertaleModLib.dll
am2r_yams/yams/UndertaleModLib.xml
am2r_yams/yams/YAMS-LIB.deps.json
am2r_yams/yams/YAMS-LIB.dll
am2r_yams/yams/YAMS-LIB.pdb
am2r_yams/yams/runtimes/unix/lib/netcoreapp3.0/System.Drawing.Common.dll
am2r_yams/yams/runtimes/win/lib/netcoreapp3.0/Microsoft.Win32.SystemEvents.dll
am2r_yams/yams/runtimes/win/lib/netcoreapp3.0/System.Drawing.Common.dll
am2r_yams/yams/sprites/texturepage.png
am2r_yams/yams/sprites/texturepageiteminfo.json
am2r_yams-2.8.4.dist-info/licenses/LICENSE-CODE
am2r_yams-2.8.4.dist-info/METADATA
am2r_yams-2.8.4.dist-info/WHEEL
am2r_yams-2.8.4.dist-info/entry_points.txt
am2r_yams-2.8.4.dist-info/top_level.txt
am2r_yams-2.8.4.dist-info/RECORD
